FlyBaseDownloads/.env
FlyBaseDownloads/FBD.py
FlyBaseDownloads/__init__.py
FlyBaseDownloads/setup.py
FlyBaseDownloads/classes/Alleles_Stocks.py
FlyBaseDownloads/classes/Annotation_Sequence.py
FlyBaseDownloads/classes/Clones.py
FlyBaseDownloads/classes/Gene_Ontology_annotation.py
FlyBaseDownloads/classes/Gene_groups.py
FlyBaseDownloads/classes/Genes.py
FlyBaseDownloads/classes/Homologs.py
FlyBaseDownloads/classes/Human_disease.py
FlyBaseDownloads/classes/Insertions.py
FlyBaseDownloads/classes/Map_conversion.py
FlyBaseDownloads/classes/Ontology_Terms.py
FlyBaseDownloads/classes/Organisms.py
FlyBaseDownloads/classes/References.py
FlyBaseDownloads/classes/Synonyms.py
FlyBaseDownloads/classes/__init__.py
FlyBaseDownloads/downloads/Downloads.py
FlyBaseDownloads/downloads/download_fasta.py
FlyBaseDownloads/downloads/download_fb.py
FlyBaseDownloads/downloads/download_json.py
FlyBaseDownloads/downloads/download_obo.py
FlyBaseDownloads/downloads/download_tsv.py
FlyBaseDownloads/utilities/__init__.py
FlyBaseDownloads/utilities/authentication.py
FlyBaseDownloads/utilities/downloads.py
FlyBaseDownloads/utilities/internet.py
FlyBaseDownloads-3.1.3.dist-info/METADATA
FlyBaseDownloads-3.1.3.dist-info/WHEEL
FlyBaseDownloads-3.1.3.dist-info/top_level.txt
FlyBaseDownloads-3.1.3.dist-info/RECORD
