Metadata-Version: 2.1
Name: FlyBaseDownloads
Version: 3.1.3
Summary: Wrapped to download FlyBase data with Python, easily and quickly.
Home-page: https://github.com/JavieraQuirozO/FBD
Author: Javiera Quiroz Olave
Author-email: javiera.quiroz@biomedica.udec.cl
License: MIT
Classifier: Development Status :: 3 - Alpha
Classifier: Intended Audience :: Science/Research
Classifier: Intended Audience :: Healthcare Industry
Classifier: License :: OSI Approved :: MIT License
Classifier: Programming Language :: Python :: 3
Requires-Python: >=3.6
Requires-Dist: pandas>=1.3.0
Requires-Dist: python-dotenv>=0.19.0
Requires-Dist: requests>=2.25.1
Requires-Dist: obonet>=0.4.0
